scan.py
dapyto-0.0.1a4.dist-info/LICENSE.txt
dapyto-0.0.1a4.dist-info/METADATA
dapyto-0.0.1a4.dist-info/WHEEL
dapyto-0.0.1a4.dist-info/entry_points.txt
dapyto-0.0.1a4.dist-info/top_level.txt
dapyto-0.0.1a4.dist-info/RECORD
