Metadata-Version: 2.1
Name: dapyto
Version: 0.0.1a4
Summary: Daniel's Python Tools
Author-email: Daniel Volk <contact@daniel-volk.com>
Maintainer-email: Daniel Volk <contact@daniel-volk.com>
License: MIT License
Project-URL: Homepage, https://github.com/daniel-volk/daniels_python_tools
Project-URL: Bug Reports, https://github.com/pypa/sampleproject/issues
Project-URL: Source, https://github.com/daniel-volk/daniels_python_tools
Keywords: python,command-line,development,tools
Classifier: Topic :: Software Development
Classifier: Topic :: System
Classifier: Topic :: Utilities
Classifier: Development Status :: 3 - Alpha
Classifier: License :: OSI Approved :: MIT License
Classifier: Programming Language :: Python :: 3 :: Only
Classifier: Operating System :: OS Independent
Classifier: Environment :: Console
Classifier: Intended Audience :: Developers
Classifier: Intended Audience :: System Administrators
Classifier: Natural Language :: English
Requires-Python: >=3.8
License-File: LICENSE.txt
Requires-Dist: click >=8.1
